pyTFM/TFM_functions.py
pyTFM/TFM_functions_for_clickpoints.py
pyTFM/__clickpoints_addon__.txt
pyTFM/__init__.py
pyTFM/_version.py
pyTFM/data_analysis.py
pyTFM/database_functions.py
pyTFM/frame_shift_correction.py
pyTFM/graph_theory_for_cell_boundaries.py
pyTFM/grid_setup_solids_py.py
pyTFM/parameters_and_strings.py
pyTFM/plotting.py
pyTFM/stress_functions.py
pyTFM/utilities_TFM.py
pyTFM/TFM_addon/Data.txt
pyTFM/TFM_addon/TFM_addon.py
pyTFM-1.3.5.dist-info/LICENSE
pyTFM-1.3.5.dist-info/METADATA
pyTFM-1.3.5.dist-info/WHEEL
pyTFM-1.3.5.dist-info/top_level.txt
pyTFM-1.3.5.dist-info/RECORD
