Metadata-Version: 2.1
Name: pyTFM
Version: 1.3.5
Summary: traction force microscopy and monolayer stress microscopy of cell sheets and isolated patches
Home-page: https://pytfm.readthedocs.io/
Download-URL: https://github.com/fabrylab/pyTFM.git
Author: Andreas Bauer
Author-email: andreas.b.bauer@fau.de
License: GPLv3
Keywords: traction force microscopy,finite elements
Platform: UNKNOWN
License-File: LICENSE
Requires-Dist: numpy
Requires-Dist: cython
Requires-Dist: openpiv (==0.22.0)
Requires-Dist: pyyaml
Requires-Dist: scipy
Requires-Dist: scikit-image (>=0.18.1)
Requires-Dist: matplotlib (>=2.1.2)
Requires-Dist: tqdm
Requires-Dist: solidspy
Requires-Dist: clickpoints (>=1.9.6)
Requires-Dist: natsort
